<xml xmlns="http://www.w3.org/1999/xhtml"><block type="onfirstboot" id="onfirstboot" x="42" y="29"><next><block type="lampinstall" id="]T#BEY(=8EdaUXwF-C,U"><field name="1">cncpi</field><next><block type="bootbehaviour" id="JnnLA+QLnt?Kk?m9*G]-"><field name="1">Desktop logged in</field><next><block type="sethostname" id="=QCnOT@ub_]L8U;|+y)}"><field name="1">cncpi</field><next><block type="runcommand" id="]M/bu=pK/h*q(:IsuHge"><field name="1">systemctl enable ssh</field><field name="2">root</field><next><block type="runcommand" id="N4o~v}#)kAFsVb;4m=Oc"><field name="1">git clone https://github.com/ArnyminerZ/CNCPi.git /temp/install</field><field name="2">root</field><next><block type="runcommand" id="Kjsu/rVao--Ud#5N+.MD"><field name="1">/temp/install/CNCPi/install.sh</field><field name="2">root</field><next><block type="deletefile" id="%6f/w|TRl6XbGobp/Rj!"><field name="1">/temp/install/CNCPi</field><next><block type="deletefile" id="h-)T78k*?X0]}coxm_6|"><field name="1">/temp/install</field><next><block type="deletefile" id="w|K3jt+Db=;3ys*hvs#1"><field name="1">/temp</field><next><block type="reboot" id="djod;GGcMs7N|Ri{h}}+"></block></next></block></next></block></next></block></next></block></next></block></next></block></next></block></next></block></next></block></next></block><block type="onboot" id="%rjEH@K@!-BYFZW]2=xu" x="425" y="27"><next><block type="vncenable" id="c[xn1eCY[3(Dz^PqA;rn"><field name="1">Enable</field><next><block type="runcommand" id="j+p%RWMTC=V,zrr(!bY_"><field name="1">sudo systemctl start ssh</field><field name="2">root</field></block></next></block></next></block></xml>